drowsy_server/__init__.py
drowsy_server/__main__.py
drowsy_server/example.py
drowsy_server/interface.py
drowsy_server-0.2.1.dist-info/entry_points.txt
drowsy_server-0.2.1.dist-info/LICENSE
drowsy_server-0.2.1.dist-info/WHEEL
drowsy_server-0.2.1.dist-info/METADATA
drowsy_server-0.2.1.dist-info/RECORD
